_serpent_cffi.abi3.so
akris/VERSION
akris/__init__.py
akris/api_service.py
akris/asked_for.py
akris/caribou.py
akris/client.py
akris/config.py
akris/console_dispatch.py
akris/database.py
akris/exception_dispatch.py
akris/filter.py
akris/json_stream_parser.py
akris/log_config.py
akris/main.py
akris/message_factory.py
akris/net_chain.py
akris/peer.py
akris/pest_dispatch.py
akris/pest_service.py
akris/presence.py
akris/scheduler.py
akris/serpent.py
akris/singleton.py
akris/singleton_registry.py
akris/sqlite3worker.py
akris/station.py
akris/version.py
akris/c_serpent/__init__.py
akris/c_serpent/_serpent_cffi.c
akris/c_serpent/c_serpent.c
akris/c_serpent/config.h
akris/c_serpent/crypto.h
akris/c_serpent/def.h
akris/c_serpent/serp_test.py
akris/c_serpent/serpent.py
akris/c_serpent/serpent_build.py
akris/c_serpent/spec.h
akris/c_serpent/type.h
akris/c_serpent/lib/base64.c
akris/c_serpent/lib/hmac.c
akris/c_serpent/lib/hmac.h
akris/c_serpent/lib/serpent.c
akris/c_serpent/lib/serpent.h
akris/c_serpent/lib/sha.c
akris/c_serpent/lib/sha.h
akris/console_command_executors/__init__.py
akris/console_command_executors/at.py
akris/console_command_executors/broadcast_text.py
akris/console_command_executors/broadcast_text_m.py
akris/console_command_executors/console_command_executor.py
akris/console_command_executors/direct_text.py
akris/console_command_executors/direct_text_m.py
akris/console_command_executors/genkey.py
akris/console_command_executors/handle.py
akris/console_command_executors/help.py
akris/console_command_executors/key.py
akris/console_command_executors/knob.py
akris/console_command_executors/message_stats.py
akris/console_command_executors/page.py
akris/console_command_executors/page_around.py
akris/console_command_executors/page_down.py
akris/console_command_executors/page_up.py
akris/console_command_executors/peer.py
akris/console_command_executors/report_presence.py
akris/console_command_executors/reset_database.py
akris/console_command_executors/search.py
akris-1.0.0.dist-info/licenses/LICENSE.TXT
akris-1.0.0.dist-info/METADATA
akris-1.0.0.dist-info/WHEEL
akris-1.0.0.dist-info/entry_points.txt
akris-1.0.0.dist-info/top_level.txt
akris-1.0.0.dist-info/RECORD
