Metadata-Version: 2.4
Name: akris
Version: 1.0.0
Summary: A pest implementation
Home-page: http://alethepedia.com/akris
Author: Adam Thorsen
Author-email: awt@fastmail.fm
License: VPL
Keywords: p2p pest chat
Classifier: Development Status :: 3 - Alpha
Classifier: Intended Audience :: Developers
Classifier: License :: Other/Proprietary License
Classifier: Natural Language :: English
Classifier: Programming Language :: Python :: 3
Requires-Python: >=3.6
License-File: LICENSE.TXT
Requires-Dist: cffi
Requires-Dist: setuptools
Provides-Extra: dev
Requires-Dist: black; extra == "dev"
Requires-Dist: pytest; extra == "dev"
Requires-Dist: pylint; extra == "dev"
Requires-Dist: pyinstaller; extra == "dev"
Requires-Dist: staticx; extra == "dev"
Requires-Dist: markdown2; extra == "dev"
Dynamic: author
Dynamic: author-email
Dynamic: classifier
Dynamic: description
Dynamic: description-content-type
Dynamic: home-page
Dynamic: keywords
Dynamic: license
Dynamic: license-file
Dynamic: provides-extra
Dynamic: requires-dist
Dynamic: requires-python
Dynamic: summary
